<?xml version="1.0" encoding="utf-8" ?>
<dwsync>
<file name="hdrLatinAmerica.jpg" server="dev.dance4peace.org" local="130214919670994948" remote="130213461000000000" Dst="2" />
<file name="hdrThePhilippines.jpg" server="dev.dance4peace.org" local="130214919671930960" remote="130213461000000000" Dst="2" />
<file name="hdrUS.jpg" server="dev.dance4peace.org" local="130214919675675008" remote="130213461000000000" Dst="2" />
<file name="hdrEurope.jpg" server="dev.dance4peace.org" local="130214918281486502" remote="130214811000000000" Dst="2" />
<file name="sidebarLatinAmerica.png" server="dev.dance4peace.org" local="130250453035243664" remote="130211668800000000" Dst="2" />
<file name="sidebarUS.png" server="dev.dance4peace.org" local="130250453041951750" remote="130211668800000000" Dst="2" />
<file name="sidebarsidebarThePhilippines.png" server="dev.dance4peace.org" local="130211608659345024" remote="130211505600000000" Dst="2" />
<file name="hdrGlobalMovement.jpg" server="dev.dance4peace.org" local="130214919667874908" remote="130213461000000000" Dst="2" />
<file name="sidebarThePhilippines.png" server="dev.dance4peace.org" local="130250453038675708" remote="130211668800000000" Dst="2" />
</dwsync>